workspace_extractor/__init__.py
workspace_extractor/manager.py
workspace_extractor/mapping.py
workspace_extractor/sizing.py
workspace_extractor/exceptions/__init__.py
workspace_extractor/exceptions/no_cluster_events_error.py
workspace_extractor/utils/__init__.py
workspace_extractor/utils/util.py
workspace_extractor/utils/util_file.py
snow_workspace_extractor-0.1.1.dist-info/METADATA
snow_workspace_extractor-0.1.1.dist-info/WHEEL
snow_workspace_extractor-0.1.1.dist-info/licenses/LICENSE
snow_workspace_extractor-0.1.1.dist-info/RECORD
