Metadata-Version: 2.4
Name: snow-workspace-extractor
Version: 0.1.1
Summary: Snowflake Wokspace Extractor is a Python package that provides a simple way to extract and analyze data from Snowflake workspaces. It allows users to retrieve metadata, query history, and other relevant information from their Snowflake workspaces, enabling better understanding and management of their data environment.
Project-URL: Documentation, https://github.com/Snowflake-Labs/Workspace-Estimator/blob/main/README.md
Project-URL: Issues, https://github.com/Snowflake-Labs/Workspace-Estimator/issues
Project-URL: Source, https://github.com/Snowflake-Labs/Workspace-Estimator
Author-email: "Snowflake, Inc." <snowflake-python-libraries-dl@snowflake.com>
License: Apache License, Version 2.0
License-File: LICENSE
Keywords: Snowflake,Snowpark,analytics,cloud,data,data-analysis,data-analytics,data-engineering,data-management,data-processing,data-science,data-visualization,we,workspace extractor
Classifier: Development Status :: 4 - Beta
Classifier: Environment :: Console
Classifier: Environment :: Other Environment
Classifier: Intended Audience :: Developers
Classifier: Intended Audience :: Education
Classifier: Intended Audience :: Information Technology
Classifier: Intended Audience :: System Administrators
Classifier: License :: OSI Approved :: Apache Software License
Classifier: Operating System :: OS Independent
Classifier: Programming Language :: Python :: 3 :: Only
Classifier: Topic :: Scientific/Engineering :: Information Analysis
Classifier: Topic :: Software Development
Classifier: Topic :: Software Development :: Libraries
Classifier: Topic :: Software Development :: Libraries :: Application Frameworks
Classifier: Topic :: Software Development :: Libraries :: Python Modules
Requires-Python: >=3.10
Requires-Dist: pandas==2.2.3
Requires-Dist: requests==2.32.3
Requires-Dist: tqdm==4.67.1
Provides-Extra: development
Requires-Dist: coverage>=7.6.7; extra == 'development'
Requires-Dist: deepdiff>=8.0.0; extra == 'development'
Requires-Dist: hatchling==1.25.0; extra == 'development'
Requires-Dist: pre-commit>=4.0.1; extra == 'development'
Requires-Dist: pytest-cov>=6.0.0; extra == 'development'
Requires-Dist: pytest>=8.3.3; extra == 'development'
Requires-Dist: setuptools>=70.0.0; extra == 'development'
Requires-Dist: twine==5.1.1; extra == 'development'
